deepl_tr/__init__.py
deepl_tr/__main__.py
deepl_tr/__main__.py-
deepl_tr/__main__2.py
deepl_tr/access_localstorage.py
deepl_tr/css/brands.css
deepl_tr/css/fontawesome.css
deepl_tr/css/solid.css
deepl_tr/csv2list.py
deepl_tr/deepl_tr.py
deepl_tr/favicon.ico
deepl_tr/gen_html.py
deepl_tr/host-port-option.txt
deepl_tr/html/index.html
deepl_tr/html/second.html
deepl_tr/html/tab1.html
deepl_tr/html/tab2.html
deepl_tr/html/tab3.html
deepl_tr/httpserver.py
deepl_tr/lang_pairs.py
deepl_tr/list2csv.py
deepl_tr/loadtext.py
deepl_tr/main_webui2.py
deepl_tr/static/ag-grid-community.js
deepl_tr/static/all.css
deepl_tr/static/all.js
deepl_tr/static/daisyui2.47.0.css
deepl_tr/static/tailwind-plugins.css
deepl_tr/templates/_navigation.html
deepl_tr/templates/aggrid-table.html
deepl_tr/templates/aggrid-table1.html
deepl_tr/templates/aggrid-table2.html
deepl_tr/templates/base.html
deepl_tr/templates/base1.html
deepl_tr/templates/child.html
deepl_tr/templates/dashboard.html
deepl_tr/templates/deepl-port.html
deepl_tr/templates/deepl-tr-base - Copy.html
deepl_tr/templates/deepl-tr-base.html
deepl_tr/templates/header.html
deepl_tr/templates/login.html
deepl_tr/templates/macros.html
deepl_tr/templates/navbar-active.html
deepl_tr/templates/result.html
deepl_tr/templates/tab1.html
deepl_tr/templates/tab2.html
deepl_tr/templates/tab3.html
deepl_tr/templates/tab3a.html
deepl_tr/templates/tablog.html
deepl_tr/templates/tabs.html
deepl_tr/templates/text.html
deepl_tr/tmpl/aggrid-table1.html
deepl_tr/tmpl/aggrid-table2.html
deepl_tr/tmpl/deepl-tr-base.html
deepl_tr/tmpl/navbar-active.html
deepl_tr/tmpl/tab1.html
deepl_tr/tmpl/tab2.html
deepl_tr/tmpl/tab3.html
deepl_tr/webfonts/fa-brands-400.eot
deepl_tr/webfonts/fa-brands-400.svg
deepl_tr/webfonts/fa-brands-400.ttf
deepl_tr/webfonts/fa-brands-400.woff
deepl_tr/webfonts/fa-brands-400.woff2
deepl_tr/webfonts/fa-regular-400.eot
deepl_tr/webfonts/fa-regular-400.svg
deepl_tr/webfonts/fa-regular-400.ttf
deepl_tr/webfonts/fa-regular-400.woff
deepl_tr-0.1.0a2.dist-info/entry_points.txt
deepl_tr-0.1.0a2.dist-info/LICENSE
deepl_tr-0.1.0a2.dist-info/WHEEL
deepl_tr-0.1.0a2.dist-info/METADATA
deepl_tr-0.1.0a2.dist-info/RECORD
