Metadata-Version: 2.1
Name: deepl-tr
Version: 0.1.0a2
Summary: deepl translate using deepl-fastapi and webui2
Home-page: https://github.com/ffreemt/deepl-tr-webui
License: MIT
Author: ffreemt
Requires-Python: >=3.8.3,<4.0.0
Classifier: License :: OSI Approved :: MIT License
Classifier: Programming Language :: Python :: 3
Classifier: Programming Language :: Python :: 3.9
Classifier: Programming Language :: Python :: 3.10
Requires-Dist: Jinja2 (>=3.1.2,<4.0.0)
Requires-Dist: cchardet (>=2.1.7,<3.0.0)
Requires-Dist: charset-normalizer (>=3.0.1,<4.0.0)
Requires-Dist: deepl-scraper-pp2 (>=0.1.0a2,<0.1.0)
Requires-Dist: httpx (>=0.23.3,<0.24.0)
Requires-Dist: icecream (>=2.1.1,<3.0.0)
Requires-Dist: install (>=1.3.5,<2.0.0)
Requires-Dist: loguru (>=0.6.0,<0.7.0)
Requires-Dist: logzero (>=1.7.0,<2.0.0)
Requires-Dist: set-loglevel (>=0.1.2,<0.2.0)
Requires-Dist: typer (>=0.4.1,<0.5.0)
Requires-Dist: webui2 (>=2.0.6,<3.0.0)
Project-URL: Repository, https://github.com/ffreemt/deepl-tr-webui
